labscript_suite/__init__.py
labscript_suite/__version__.py
labscript_suite-3.2.0.dist-info/LICENSE.txt
labscript_suite-3.2.0.dist-info/METADATA
labscript_suite-3.2.0.dist-info/WHEEL
labscript_suite-3.2.0.dist-info/top_level.txt
labscript_suite-3.2.0.dist-info/RECORD
