Metadata-Version: 2.1
Name: labscript-suite
Version: 3.2.0
Summary: Meta-package for the labscript suite experiment control and automation system
Home-page: http://labscriptsuite.org
Author: The labscript suite community
Author-email: labscriptsuite@googlegroups.com
License: BSD
Project-URL: Source Code, https://github.com/labscript-suite/labscript-suite
Project-URL: Download, https://github.com/labscript-suite/labscript-suite/releases
Project-URL: Tracker, https://github.com/labscript-suite/labscript-suite/issues
Keywords: experiment control automation
Classifier: License :: OSI Approved :: BSD License
Classifier: Programming Language :: Python :: 3 :: Only
Classifier: Programming Language :: Python :: 3.6
Classifier: Programming Language :: Python :: 3.7
Classifier: Programming Language :: Python :: 3.8
Classifier: Programming Language :: Python :: 3.9
Classifier: Programming Language :: Python :: 3.10
Classifier: Programming Language :: Python :: 3.11
Requires-Python: >=3.6
License-File: LICENSE.txt
Requires-Dist: importlib-metadata
Requires-Dist: setuptools-scm (>=4.1.0)
Requires-Dist: blacs (>=3.2.0)
Requires-Dist: labscript (>=3.3.0)
Requires-Dist: labscript-devices (>=3.2.0)
Requires-Dist: labscript-utils (>=3.3.0)
Requires-Dist: lyse (>=3.2.1)
Requires-Dist: runmanager (>=3.2.0)
Requires-Dist: runviewer (>=3.2.0)
Provides-Extra: docs
Requires-Dist: Sphinx (==4.4.0) ; extra == 'docs'
Requires-Dist: sphinx-rtd-theme (==0.5.2) ; extra == 'docs'
Requires-Dist: recommonmark (==0.6.0) ; extra == 'docs'
Requires-Dist: m2r (==0.2.1) ; extra == 'docs'
Requires-Dist: mistune (<2.0.0) ; extra == 'docs'
Provides-Extra: nidaqmx
Requires-Dist: PyDAQmx ; extra == 'nidaqmx'
Provides-Extra: nivision
Requires-Dist: PyNIVision ; extra == 'nivision'
Provides-Extra: pyqt
Requires-Dist: PyQt5 ; extra == 'pyqt'
Provides-Extra: spincore
Requires-Dist: spinapi ; extra == 'spincore'
